picklejson/__init__.py
picklejson/context.py
picklejson/decoder.py
picklejson/decorator.py
picklejson/encoder.py
picklejson/functions.py
picklejson/interfaces.py
picklejson-1.1.0.dist-info/LICENSE
picklejson-1.1.0.dist-info/WHEEL
picklejson-1.1.0.dist-info/METADATA
picklejson-1.1.0.dist-info/RECORD
